[
  {
    "pid": "89",
    "trial": 9,
    "representation": "v3_maximum",
    "model": "o4-mini",
    "neighbors": [
      {
        "slug": "jamie_dimon",
        "name": "Jamie Dimon",
        "price": 5000
      },
      {
        "slug": "michael_saylor",
        "name": "Michael Saylor",
        "price": 1000000
      },
      {
        "slug": "peter_schiff",
        "name": "Peter Schiff",
        "price": 3000
      },
      {
        "slug": "larry_fink",
        "name": "Larry Fink",
        "price": 150000
      }
    ],
    "celeb_mean": 289500,
    "baseline_price": 50000,
    "recognition_response": "Here\u2019s how I\u2019d reflect on each forecast, speaking honestly as myself\u2014a retired Midwestern woman who follows mainstream news, values clear, reliable sources, and has only moderate appetite for deep financial research.\n\n1. Jamie Dimon ($5,000)  \n   1. Do I know who he is? Yes.  \n   2. What I know and trust level:  \n      - He\u2019s the long-time CEO of JPMorgan Chase, often quoted on CNN, NPR, and in The New York Times.  \n      - He\u2019s been openly skeptical of Bitcoin in the past, calling it a \u201cfraud\u201d and warning of bank risks.  \n      - I trust his broad banking-industry insight\u2014he runs one of the largest banks\u2014but I also recognize he may have a conflict of interest (traditional banks vs. decentralized crypto). So I\u2019d give him moderate credibility on overall financial stability, but I\u2019d discount a bit for his institutional bias against BTC.  \n\n2. Michael Saylor ($1,000,000)  \n   1. Do I know who he is? Vaguely.  \n   2. Would I look him up? Yes.  \n      - I\u2019d discover he\u2019s the Executive Chairman of MicroStrategy, a software company that has turned itself into one of Bitcoin\u2019s biggest corporate holders. I\u2019d read headlines like \u201cMicroStrategy Buys More Bitcoin.\u201d  \n      - That tells me he\u2019s extremely bullish\u2014probably emotionally and financially tied to BTC\u2019s upside. I\u2019d respect his conviction and deep focus on Bitcoin as \u201cdigital gold,\u201d but I\u2019d also see his forecast as potentially over-optimistic. I\u2019d treat his $1 million target as coming from someone who\u2019s heavily invested in making that narrative succeed.  \n\n3. Peter Schiff ($3,000)  \n   1. Do I know who he is? Vaguely.  \n   2. Would I look him up? Probably not\u2014I\u2019ve come across him often enough.  \n      - I know he\u2019s a gold-bug, runs Euro Pacific Capital, and hosts a financial podcast where he consistently argues that Bitcoin is a bubble and gold is the only sound store of value.  \n      - I trust that his bearish predictions reflect a coherent worldview (favoring precious metals over crypto), but I also know he has his own bias. His $3 000 forecast fits his long-standing argument that Bitcoin has little intrinsic value. I\u2019d weigh his view as earnest but highly colored by his gold-centered business model.  \n\n4. Larry Fink ($150,000)  \n   1. Do I know who he is? Vaguely.  \n   2. Would I look him up? Yes.  \n      - I\u2019d find he\u2019s the CEO of BlackRock, the world\u2019s largest asset manager, recently behind filings for a Bitcoin ETF.  \n      - That tells me he\u2019s taking a pragmatic, institutional approach: he sees enough client demand to offer regulated BTC exposure. His $150 000 target is a middle-of-the-road consensus\u2014bullish but not fanatic. I\u2019d consider him fairly credible because he\u2019s responding to real asset flows, though he may be cautious so as not to spook traditional investors.  \n\nIn sum, I recognize all four, though only Jamie Dimon and Peter Schiff ring as \u201cfull names\u201d to me from regular news. I\u2019d look up Saylor and Fink to ground their backgrounds\u2014and that context would lead me to discount the extremes (Dimon\u2019s super-bearish view and Saylor\u2019s super-bullish one) and give more weight to someone like Fink, whose forecast sits between institutional adoption and market realism.",
    "type_a_raw": "140000",
    "type_a_prediction": 140000,
    "recognition_response_b": "Here\u2019s how I\u2019d think about each of these four voices before making up my own mind:\n\n1. Jamie Dimon (JPMorgan CEO) \u2013 5,000 USD prediction  \n   1. Do I know him? Yes.  \n   2. What do I know and how much do I trust him?  \n      \u2022 He\u2019s been at the helm of JPMorgan Chase forever, one of the biggest banks in the world.  \n      \u2022 He\u2019s famously skeptical of Bitcoin\u2014calls it a \u201cpet rock.\u201d  \n      \u2022 I respect his banking-industry expertise and track record running a huge institution, but I also know he has an incentive to protect traditional banking. So his anti-crypto stance probably reflects business self-interest as much as pure analysis. I\u2019d weigh his caution heavily but not take it as gospel.  \n   3. (n/a\u2014he\u2019s familiar to me.)\n\n2. Michael Saylor (MicroStrategy Executive Chairman) \u2013 1,000,000 USD prediction  \n   1. Do I know him? Vaguely.  \n   2. If \u201cvaguely\u201d \u2013 would I look him up? Yes.  \n      \u2022 A quick check shows he\u2019s the guy who turned a software-analytics firm into what\u2019s basically a Bitcoin holding company. He\u2019s been on CNBC and in The New York Times talking about \u201cdigital energy\u201d and hoarding sats like there\u2019s no tomorrow.  \n      \u2022 That tells me he\u2019s highly committed\u2014maybe too committed\u2014to the upside. He\u2019s staking his company on Bitcoin, so he has a very strong bias.  \n      \u2022 After that background I\u2019d treat his million-dollar call as aspirational marketing more than sober forecasting.  \n\n3. Peter Schiff (Euro Pacific Capital CEO, host of The Peter Schiff Show) \u2013 3,000 USD prediction  \n   1. Do I know him? Vaguely.  \n   2. If \u201cvaguely\u201d \u2013 would I look him up? Yes.  \n      \u2022 A quick search reminds me he\u2019s the classic gold-bug, Austrian-economics type, always warning of financial doom and preferring physical gold.  \n      \u2022 He dismisses Bitcoin as a bubble and points to his decades-old track record in gold\u2014though by many accounts he underperformed other asset managers.  \n      \u2022 Knowing that, I\u2019d see his $3,000 forecast as motivated by his own gold advocacy. I\u2019d factor in that bias and not see him as a neutral observer.  \n\n4. Larry Fink (BlackRock CEO) \u2013 150,000 USD prediction  \n   1. Do I know him? Yes.  \n   2. What do I know and how much do I trust him?  \n      \u2022 He runs the biggest asset manager in the world. Lately he\u2019s been talking up institutional Bitcoin ETFs and client interest in digital assets.  \n      \u2022 He\u2019s not a hard-core believer like Saylor, but he wouldn\u2019t be making that call unless major institutions were asking for a seat at the table.  \n      \u2022 I\u2019d trust his view more than Dimon\u2019s outright dismissal, because Fink is responding to actual client demand. He\u2019s less ideological, more data-driven\u2014but still cautious.  \n   3. (n/a\u2014he\u2019s familiar to me.)\n\nBottom line  \nAll four have strong incentives shaping their views: Dimon to protect banks, Saylor to pump Bitcoin, Schiff to champion gold, Fink to serve institutional demand. I\u2019d take each prediction with a big grain of salt, look at my own research, and lean toward a middle-of-the-road forecast rather than any extreme.",
    "type_b_raw": "PREDICTION: 70000  \nREASONING: I discount Dimon\u2019s outright dismissal and Schiff\u2019s gold-bug stance as too bearish, and I view Saylor\u2019s million-dollar call as overly promotional. Fink\u2019s 150,000 forecast feels grounded in real client demand and growing ETF inflows. Accounting for regulatory uncertainty and Bitcoin\u2019s historic volatility, a mid-range outcome seems most plausible. This balances my cautious trust in institutional data with a moderate appetite for upside under uncertainty.",
    "type_b_prediction": 70000,
    "type_b_reasoning": "I discount Dimon\u2019s outright dismissal and Schiff\u2019s gold-bug stance as too bearish, and I view Saylor\u2019s million-dollar call as overly promotional. Fink\u2019s 150,000 forecast feels grounded in real client demand and growing ETF inflows. Accounting for regulatory uncertainty and Bitcoin\u2019s historic volatility, a mid-range outcome seems most plausible. This balances my cautious trust in institutional data with a moderate appetite for upside under uncertainty."
  },
  {
    "pid": "89",
    "trial": 30,
    "representation": "v3_maximum",
    "model": "o4-mini",
    "neighbors": [
      {
        "slug": "larry_fink",
        "name": "Larry Fink",
        "price": 150000
      },
      {
        "slug": "jamie_dimon",
        "name": "Jamie Dimon",
        "price": 5000
      },
      {
        "slug": "nouriel_roubini",
        "name": "Nouriel Roubini",
        "price": 2000
      },
      {
        "slug": "cathie_wood",
        "name": "Cathie Wood",
        "price": 500000
      }
    ],
    "celeb_mean": 164250,
    "baseline_price": 50000,
    "recognition_response": "Here\u2019s my take on each of them, speaking as me\u2014a retired Midwestern woman who reads NPR and the NY Times, does a bit of online fact\u2010checking, and trusts traditional finance voices cautiously when it comes to crypto.\n\n1. Larry Fink (BlackRock, $150 000)  \n  \u2022 Do I know him? Vaguely.  \n  \u2022 Would I look him up? Yes\u2014I\u2019d check his bio. I\u2019d find he\u2019s CEO of the world\u2019s largest asset manager, has been tipping his toe into a spot Bitcoin ETF, and usually errs on the side of large institutional flows.  \n  \u2022 How that shapes my view: I\u2019d give his number some weight\u2014he sees big institutional demand\u2014but I\u2019d temper it because BlackRock is just entering crypto and he\u2019s not traditionally a crypto evangelist.\n\n2. Jamie Dimon (JPMorgan Chase, $5 000)  \n  \u2022 Do I know him? Yes.  \n  \u2022 What I know & trust level: He\u2019s the outspoken JPMorgan CEO famous for calling Bitcoin a \u201cfraud\u201d (though JPMorgan publishes research on it). I respect his macro calls in banking, but I know he has a bias to protect legacy banks.  \n  \u2022 Trust on this? Low to moderate. His deep-value banking view makes him bearish on crypto, but that bias suggests he\u2019s anchoring low.\n\n3. Nouriel Roubini (NYU Stern/Atlas, $2 000)  \n  \u2022 Do I know him? Yes.  \n  \u2022 What I know & trust level: He\u2019s \u201cDr. Doom,\u201d predicted the 2008 crisis, and is a fierce anti-crypto skeptic. He publishes economic analyses but often dismisses blockchain entirely.  \n  \u2022 Trust on this? Low on Bitcoin. His rigorous academic style I respect, but he seems ideologically fixed against crypto, so I\u2019d discount his ultra-bearish take.\n\n4. Cathie Wood (ARK Invest, $500 000)  \n  \u2022 Do I know her? Vaguely.  \n  \u2022 Would I look her up? Yes\u2014I\u2019d learn she runs ARK, is famous for big-picture bets on disruptive tech (Tesla, genomics, crypto), and she\u2019s consistently ultra-bullish.  \n  \u2022 How that shapes my view: I admire her innovation focus but know her forecasts often stretch optimism. I\u2019d file her estimate at the high end of the spectrum but treat it as a best-case scenario rather than my baseline.",
    "type_a_raw": "100000",
    "type_a_prediction": 100000,
    "recognition_response_b": "Here\u2019s my honest take, one by one:\n\n1. Larry Fink (BlackRock)  \n  1. Do I know him?  vaguely.  \n  2. What I know and trust level: He runs BlackRock, the world\u2019s largest asset manager. I\u2019ve seen him quoted on CNBC and in the New York Times talking about institutional money flows. I respect his institutional\u2010investment expertise, but I\u2019m not sure how deep his crypto knowledge is\u2014he may be gauging client demand more than the technology\u2019s fundamentals. I\u2019d trust him moderately when it comes to big\u2010picture flows, less so on a precise Bitcoin price.  \n  3. Would I look him up? Yes, because I only know him by reputation. A quick search would confirm his track record managing trillions in assets and advising big pension funds. That would slightly increase my confidence that his $150K figure reflects serious institutional modeling, though I\u2019d still take a margin of error around any bold forecast.\n\n2. Jamie Dimon (JPMorgan CEO)  \n  1. Do I know him?  yes.  \n  2. What I know and trust level: He\u2019s led JPMorgan Chase for years, very influential on banking regulation and markets. He\u2019s notoriously bearish on Bitcoin\u2014calls it a \u201cpet rock\u201d and worries about fraud and volatility. I think he speaks from a banking\u2010industry perspective that sees crypto as competition, so there\u2019s bias. I\u2019d trust his caution on risk and speculation, but suspect his low $5,000 target is partly defensive.  \n  3. (Not applicable\u2014already familiar.)\n\n3. Nouriel Roubini (NYU Stern)  \n  1. Do I know him?  vaguely.  \n  2. What I know and trust level: He\u2019s \u201cDr. Doom,\u201d predicted the 2008 crash, now famously anti\u2010crypto. He\u2019s a respected academic on macroeconomics and crises, so his wariness about bubbles carries weight. But he\u2019s so vocally negative on Bitcoin that it feels ideological at times. I\u2019d give him moderate trust on warning about volatility and scams, but I wouldn\u2019t take his $2,000 floor as gospel\u2014he tends to play devil\u2019s advocate.  \n  3. Would I look him up? Possibly, to remind myself of his career highlights and criticisms. I\u2019d see he\u2019s been right on some crises but has a reputation for extreme contrarian views. That would reinforce that his bearish case is worth hearing but may overshoot on the downside.\n\n4. Cathie Wood (ARK Invest)  \n  1. Do I know her?  yes.  \n  2. What I know and trust level: She runs ARK Invest and popularized bold targets for disruptive tech\u2014Tesla, CRISPR, Bitcoin. She uses a mix of thematic research and convex\u2010ity modeling. I admire her analytical approach to adoption curves, but her price targets can be outliers. I\u2019d view $500K as the optimistic edge of possible scenarios. I trust her insights on adoption trends, less so the exact number.  \n  3. (Not applicable\u2014already familiar.)",
    "type_b_raw": "PREDICTION: 100000  \nREASONING: I balance BlackRock\u2019s institutional outlook and ARK\u2019s adoption-curve analysis against JPMorgan\u2019s and Roubini\u2019s warnings about volatility and speculative excess. Growing corporate demand and Bitcoin\u2019s capped supply support a substantial rally by end of 2025, but regulatory hurdles and market swings temper my optimism. A $100,000 target sits comfortably between overly bullish and overly bearish forecasts. This midpoint reflects both the upside potential and the downside risks under uncertainty.",
    "type_b_prediction": 100000,
    "type_b_reasoning": "I balance BlackRock\u2019s institutional outlook and ARK\u2019s adoption-curve analysis against JPMorgan\u2019s and Roubini\u2019s warnings about volatility and speculative excess. Growing corporate demand and Bitcoin\u2019s capped supply support a substantial rally by end of 2025, but regulatory hurdles and market swings temper my optimism. A $100,000 target sits comfortably between overly bullish and overly bearish forecasts. This midpoint reflects both the upside potential and the downside risks under uncertainty."
  }
]