[
  {
    "pid": "81",
    "trial": 13,
    "representation": "v3_maximum",
    "model": "o4-mini",
    "neighbors": [
      {
        "slug": "nouriel_roubini",
        "name": "Nouriel Roubini",
        "price": 2000
      },
      {
        "slug": "elon_musk",
        "name": "Elon Musk",
        "price": 150000
      },
      {
        "slug": "warren_buffett",
        "name": "Warren Buffett",
        "price": 15000
      },
      {
        "slug": "larry_fink",
        "name": "Larry Fink",
        "price": 150000
      }
    ],
    "celeb_mean": 79250,
    "baseline_price": 50000,
    "recognition_response": "Here\u2019s my take, speaking as myself:\n\n1. Nouriel Roubini  \n  1. Do I know him? Yes.  \n  2. What I know and how much I trust him: He\u2019s an NYU Stern economist nicknamed \u201cDr. Doom,\u201d famous for calling the 2008 crisis in advance. He\u2019s been an outspoken crypto skeptic for years\u2014often arguing Bitcoin has no real value. I respect his macroeconomic pedigree and data-driven style, but I also know he often takes a contrarian, even alarmist stance. I\u2019d give his Bitcoin judgment moderate credibility: he knows global finance cold, but his strong anti-crypto bias means I\u2019d take his $2,000 forecast with a grain of salt.  \n  3. \u2014  \n\n2. Elon Musk  \n  1. Do I know him? Yes.  \n  2. What I know and how much I trust him: He\u2019s the Tesla/SpaceX CEO and a very high-profile, sometimes impulsive tweeter. He\u2019s moved markets by tweeting about Dogecoin, Bitcoin, etc. I think he\u2019s more of a marketer and showman than a dispassionate analyst\u2014he\u2019ll pump or dump crypto for fun or PR. Because of that unpredictability, I trust his $150K call very little as a sober financial forecast.  \n  3. \u2014  \n\n3. Warren Buffett  \n  1. Do I know him? Yes.  \n  2. What I know and how much I trust him: He\u2019s the longtime Berkshire Hathaway CEO, legendary value investor. He has consistently said he doesn\u2019t see intrinsic value in Bitcoin or crypto. His strength is evaluating durable businesses with cash flows\u2014crypto doesn\u2019t fit that mold. I respect his overall market wisdom and long-term orientation, but since he typically avoids novel asset classes, he\u2019s not an expert on crypto specifically. I\u2019d view his $15K prediction as reflective of skepticism about crypto\u2019s store-of-value case, so I give it moderate weight.  \n  3. \u2014  \n\n4. Larry Fink  \n  1. Do I know him? Vaguely.  \n  2. Would I look him up? Yes\u2014I\u2019d check a quick profile. I\u2019d learn he\u2019s CEO of BlackRock, the world\u2019s largest asset manager, and that BlackRock has recently moved into the Bitcoin-ETF race. He\u2019s signaling institutional acceptance of crypto and likely sees big inflows from pension funds and huge portfolios. Knowing that, I\u2019d treat his $150K forecast as coming from someone betting on massive institutional adoption and capital flows, though he\u2019s also motivated to paint a bullish picture for his own business. I\u2019d weight his view as \u201cinstitutional hype potential\u201d more than dispassionate valuation\u2014but I\u2019d respect the logic that trillions under management could push price higher.  \n  3. \u2014",
    "type_a_raw": "75000",
    "type_a_prediction": 75000,
    "recognition_response_b": "Nouriel Roubini  \n1. Do you know who he is?  \n   Yes. I recognize him as \u201cDr. Doom,\u201d a NYU Stern professor and outspoken critic of crypto.  \n2. What do you know about him and how much do you trust his judgment on Bitcoin or financial markets?  \n   \u2022 He called the 2008 crisis and is well\u2010regarded on macroeconomics.  \n   \u2022 He\u2019s been sounding alarms on Bitcoin for years, arguing it has no intrinsic value.  \n   \u2022 I respect his macro background and fundamental skepticism, but his blanket bearishness often looks more ideological than data-driven. I\u2019d give his Bitcoin price call modest weight\u2014useful as a cautionary perspective but not gospel.  \n3. If no or vaguely\u2014would you look him up?  \n   Not applicable; I already know him.  \n\nElon Musk  \n1. Do you know who he is?  \n   Yes. CEO of Tesla/SpaceX, high-profile tech entrepreneur and Twitter personality.  \n2. What do you know about him and how much do you trust his judgment on Bitcoin or financial markets?  \n   \u2022 He\u2019s driven enormous market swings with tweets\u2014has bought and sold crypto publicly.  \n   \u2022 He\u2019s not a trained macro or crypto specialist; his views seem partly promotional or whimsical.  \n   \u2022 I treat his price targets as entertainment rather than rigorous analysis. Trust level: low.  \n3. If no or vaguely\u2014would you look him up?  \n   Not applicable; I already know him.  \n\nWarren Buffett  \n1. Do you know who he is?  \n   Yes. Chairman/CEO of Berkshire Hathaway, legendary value investor.  \n2. What do you know about him and how much do you trust his judgment on Bitcoin or financial markets?  \n   \u2022 He\u2019s built decades of outperformance by focusing on productive, cash-generating businesses.  \n   \u2022 He views Bitcoin as a non-productive asset and has been consistently bearish.  \n   \u2022 I highly respect his investment track record and philosophy, but recognize that his value framework may underweight non-traditional stores of value. I trust his caution but wouldn\u2019t assume he has special insight into the crypto market\u2019s network effects. Trust level: moderate-high on fundamentals, lower on sizing the crypto boom.  \n3. If no or vaguely\u2014would you look him up?  \n   Not applicable; I already know him.  \n\nLarry Fink  \n1. Do you know who he is?  \n   Yes. CEO of BlackRock, the world\u2019s largest asset manager.  \n2. What do you know about him and how much do you trust his judgment on Bitcoin or financial markets?  \n   \u2022 He\u2019s at the center of institutional capital flows and has been moving BlackRock into Bitcoin vehicles.  \n   \u2022 His optimism reflects growing institutional demand but also serves as positive PR for his firm\u2019s crypto offerings.  \n   \u2022 I respect that he sees real money moving in, so I give his $150K forecast some weight\u2014especially as a signal of institutional adoption\u2014while discounting a possible marketing tilt. Trust level: moderate.  \n3. If no or vaguely\u2014would you look him up?  \n   Not applicable; I already know him.",
    "type_b_raw": "PREDICTION: 65000  \nREASONING: I weight Larry Fink\u2019s institutional adoption signal more heavily than Elon Musk\u2019s promotional hype but still discount potential marketing bias, and I give Warren Buffett\u2019s cautious value framework significant credence while acknowledging crypto\u2019s network effects. Nouriel Roubini\u2019s deep skepticism keeps me realistic about volatility and regulatory risk. Blending these views, I anchor around the midpoint of credible forecasts and adjust for likely slower adoption and macro headwinds. This yields a cautious-but-optimistic target near $65 000 by end of 2025.",
    "type_b_prediction": 65000,
    "type_b_reasoning": "I weight Larry Fink\u2019s institutional adoption signal more heavily than Elon Musk\u2019s promotional hype but still discount potential marketing bias, and I give Warren Buffett\u2019s cautious value framework significant credence while acknowledging crypto\u2019s network effects. Nouriel Roubini\u2019s deep skepticism keeps me realistic about volatility and regulatory risk. Blending these views, I anchor around the midpoint of credible forecasts and adjust for likely slower adoption and macro headwinds. This yields a cautious-but-optimistic target near $65 000 by end of 2025."
  },
  {
    "pid": "81",
    "trial": 25,
    "representation": "v3_maximum",
    "model": "o4-mini",
    "neighbors": [
      {
        "slug": "jamie_dimon",
        "name": "Jamie Dimon",
        "price": 5000
      },
      {
        "slug": "elon_musk",
        "name": "Elon Musk",
        "price": 150000
      },
      {
        "slug": "nouriel_roubini",
        "name": "Nouriel Roubini",
        "price": 2000
      },
      {
        "slug": "jack_dorsey",
        "name": "Jack Dorsey",
        "price": 500000
      }
    ],
    "celeb_mean": 164250,
    "baseline_price": 50000,
    "recognition_response": "Jamie Dimon  \n1. Do I know who this person is?  \n   \u2013 Yes.  \n\n2. What do I know about him and how much do I trust his judgment on Bitcoin or financial markets?  \n   \u2013 Jamie Dimon is the long\u2010time CEO of JPMorgan Chase, one of the world\u2019s largest banks. He\u2019s been consistently skeptical of Bitcoin, calling it \u201cworthless\u201d or \u201ca fraud\u201d in the past, though he\u2019s softened his tone recently by exploring blockchain applications.  \n   \u2013 Trust level: Moderate for traditional finance-and-risk perspectives, low for unbiased crypto analysis. As head of a major bank, he has first-hand data on financial stability, but he also has an institutional incentive to downplay or dismiss a disruptive, decentralized asset.  \n\nElon Musk  \n1. Do I know who this person is?  \n   \u2013 Yes.  \n\n2. What do I know about him and how much do I trust his judgment on Bitcoin or financial markets?  \n   \u2013 Elon Musk runs Tesla and SpaceX and owns X. He\u2019s well known for moving markets with his tweets and has personally invested in Bitcoin and Dogecoin. He\u2019s charismatic and visionary, but also highly unpredictable.  \n   \u2013 Trust level: Low for rigorous price forecasting. He can spark short-term volatility, but his long-term price targets (like $150 K) feel more aspirational or publicity-driven than grounded in a disciplined valuation model.  \n\nNouriel Roubini  \n1. Do I know who this person is?  \n   \u2013 Vaguely.  \n\n2. Would I look him up before forming an opinion?  \n   \u2013 Yes.  \n\n   What would I likely find and how would that change my view of his prediction?  \n   \u2013 I\u2019d learn he\u2019s a professor at NYU Stern, nicknamed \u201cDr. Doom\u201d for predicting the 2008 crisis. He\u2019s one of the most vocal Bitcoin skeptics, calling it a \u201cmother of all bubbles.\u201d He tends to emphasize regulatory risk, fraud, and volatility.  \n   \u2013 After that, I\u2019d see his $2 K forecast as a natural extension of his bearish framing. I\u2019d give weight to his risk-focused analysis but also note that he often dismisses any potential for mainstream adoption. It would temper how bullish I get, but I wouldn\u2019t take it as gospel.  \n\nJack Dorsey  \n1. Do I know who this person is?  \n   \u2013 Yes.  \n\n2. What do I know about him and how much do I trust his judgment on Bitcoin or financial markets?  \n   \u2013 Jack Dorsey co-founded Twitter and now leads Block (formerly Square), which has invested heavily in Bitcoin. He\u2019s probably the highest-profile corporate \u201cBitcoin maximalist\u201d and has pushed Square\u2019s Cash App and Block\u2019s services around crypto.  \n   \u2013 Trust level: Moderate for bullish adoption trends but biased. He\u2019s invested both personally and through his company, so he has skin in the game. His $500 K number feels more like a statement of unwavering belief than the result of an unbiased financial model.  \n\n\u2014  \nIn sum, I know all four to varying degrees. I\u2019d weigh Dimon and Roubini on the cautious, risk-management side (but discount their institutional biases), and Musk and Dorsey on the bullish, adoption-driving side (but discount their promotional incentives). I\u2019d then form my own middle-of-the-road forecast, perhaps anchored around current institutional adoption trends rather than any single extreme.",
    "type_a_raw": "100000",
    "type_a_prediction": 100000,
    "recognition_response_b": "Jamie Dimon  \n1. Do I know who he is?  \n   Yes.  \n\n2. What do I know and how much do I trust him on Bitcoin/markets?  \n   \u2013 He\u2019s CEO of JPMorgan Chase and basically the face of \u201cbig banking.\u201d He\u2019s been publicly hostile to crypto for years\u2014calls Bitcoin a \u201cpet rock,\u201d worries it undercuts the banking business model.  \n   \u2013 On traditional markets and banking regulation I\u2019d give him fairly high credibility\u2014he\u2019s been in the industry for decades and JPMorgan is huge. On Bitcoin specifically I trust him less, because he has a clear conflict: a multitrillion-dollar bank that sees crypto as a threat. His $5 K call feels more like a motivated sell-magic-than an objective long-term forecast.  \n\nElon Musk  \n1. Do I know who he is?  \n   Yes.  \n\n2. What do I know and how much do I trust him on Bitcoin/markets?  \n   \u2013 Founder/CEO of Tesla and SpaceX, owner of X/Twitter. He\u2019s driven crypto sentiment before with tweets, and he\u2019s said he still holds Bitcoin as an inflation hedge.  \n   \u2013 He\u2019s got a track record of innovation, but on social media he can be impulsive and drives volatility. I respect his tech vision, but I\u2019d take any specific price target\u2014$150 K\u2014from him with a grain of salt. He\u2019s much more of a hype driver than a sober market analyst.  \n\nNouriel Roubini  \n1. Do I know who he is?  \n   Yes, though less intimately than Dimon or Musk.  \n\n2. What do I know and how much do I trust him on Bitcoin/markets?  \n   \u2013 He\u2019s \u201cDr. Doom,\u201d an NYU economist who famously predicted the 2008 crisis. He\u2019s been one of the loudest critics of crypto, calling it the \u201cmother of all scams.\u201d  \n   \u2013 On macroeconomics I respect that he\u2019s sometimes ahead of the curve. But on crypto he\u2019s almost unremittingly negative\u2014he dismisses any possible use case or value. His $2 K call is consistent with that worldview. I\u2019d weigh his warning signals but also look for more balanced or data-driven analyses.  \n\nJack Dorsey  \n1. Do I know who he is?  \n   Yes.  \n\n2. What do I know and how much do I trust him on Bitcoin/markets?  \n   \u2013 Co-founder of Twitter, now CEO of Block (Square). He\u2019s one of the highest-profile Bitcoin evangelists, building payment rails and open-source tools around BTC.  \n   \u2013 He\u2019s technically very knowledgeable about crypto infrastructure, but also heavily vested in Bitcoin\u2019s success. His $500 K projection feels driven partly by his mission to \u201cBitcoin-ify\u201d the financial system. I respect his technical chops but discount some of his enthusiasm as self-fulfilling marketing.  \n\n\u2014  \nOverall, I know all four names. I\u2019d treat Dimon and Roubini as expert on traditional finance and macro risk but biased against crypto; Musk as a high-profile influencer with spotty forecasting record; and Dorsey as a committed builder with strong crypto bias. I\u2019d blend their views, look for independent on-chain and adoption data, and check moderately trusted sources (e.g. The Block, CoinDesk, academic papers) before settling on my own range.",
    "type_b_raw": "PREDICTION: 60000  \nREASONING: I weight Dorsey\u2019s deep commitment to Bitcoin infrastructure and Musk\u2019s inflation-hedge perspective more heavily than the outright dismissals by Dimon and Roubini, while still discounting some of the hype. Growing institutional adoption and on-chain activity support a return to mid-six-figure territory, but ongoing regulatory scrutiny and volatility cap the upside. A $60 000 forecast reflects a consensus-driven, risk-adjusted midpoint between bullish network effects and bearish fundamentals.",
    "type_b_prediction": 60000,
    "type_b_reasoning": "I weight Dorsey\u2019s deep commitment to Bitcoin infrastructure and Musk\u2019s inflation-hedge perspective more heavily than the outright dismissals by Dimon and Roubini, while still discounting some of the hype. Growing institutional adoption and on-chain activity support a return to mid-six-figure territory, but ongoing regulatory scrutiny and volatility cap the upside. A $60 000 forecast reflects a consensus-driven, risk-adjusted midpoint between bullish network effects and bearish fundamentals."
  },
  {
    "pid": "81",
    "trial": 44,
    "representation": "v3_maximum",
    "model": "o4-mini",
    "neighbors": [
      {
        "slug": "jamie_dimon",
        "name": "Jamie Dimon",
        "price": 5000
      },
      {
        "slug": "nouriel_roubini",
        "name": "Nouriel Roubini",
        "price": 2000
      },
      {
        "slug": "elon_musk",
        "name": "Elon Musk",
        "price": 150000
      },
      {
        "slug": "cathie_wood",
        "name": "Cathie Wood",
        "price": 500000
      }
    ],
    "celeb_mean": 164250,
    "baseline_price": 50000,
    "recognition_response": "Here\u2019s how I\u2019d reflect on each of those four voices before settling on my own Bitcoin forecast:\n\n1. Jamie Dimon (CEO, JPMorgan Chase)  \n1. Do I know him? Yes.  \n2. What I know & trust level:  \n  \u2013 He\u2019s one of the most\u2010powerful traditional banking CEOs in the U.S., famous for calling Bitcoin \u201ca fraud\u201d in the past.  \n  \u2013 His worldview is rooted in regulated, centralized finance\u2014he literally runs one of the world\u2019s biggest banks.  \n  \u2013 I respect his macroeconomic instincts on interest rates and banking stability, but I think he has a clear conflict of interest when it comes to decentralized crypto.  \n  \u2013 Trust on Bitcoin pricing: Low. His incentive is to protect the banking system, so I discount his $5k call as too bearish.\n\n2. Nouriel Roubini (Professor of Economics, NYU Stern; CEO, Atlas Capital)  \n1. Do I know him? Yes.  \n2. What I know & trust level:  \n  \u2013 Nicknamed \u201cDr. Doom\u201d for predicting the 2008 crisis. Highly credentialed macroeconomist, and one of crypto\u2019s most vocal skeptics.  \n  \u2013 He\u2019s built a brand on warnings about bubbles, and he\u2019s often quoted in mainstream business press.  \n  \u2013 Track record: He spotted systemic risks pre\u20102008 but also has a streak of ultra\u2010pessimism\u2014he\u2019s missed some recoveries.  \n  \u2013 Trust on Bitcoin pricing: Moderate\u2010low. I take his systemic\u2010risk warnings seriously, but his ideological opposition to crypto makes me think his $2k forecast understates potential adoption tailwinds.\n\n3. Elon Musk (CEO, Tesla & SpaceX; Owner of X)  \n1. Do I know him? Yes.  \n2. What I know & trust level:  \n  \u2013 Tech visionary, big social\u2010media presence, has moved crypto markets with off\u2010the\u2010cuff tweets (both up and down).  \n  \u2013 Not a finance professional or a crypto fundamentalist; his pronouncements often look like marketing or personal whim.  \n  \u2013 Track record: Great at generating hype and selling visions of the future, but wildly inconsistent on specifics.  \n  \u2013 Trust on Bitcoin pricing: Very low. His $150k figure feels more like a headline\u2010grabbing sound bite than a grounded valuation.\n\n4. Cathie Wood (CEO & CIO, ARK Invest)  \n1. Do I know her? Yes.  \n2. What I know & trust level:  \n  \u2013 Runs a well-known ETF family focused on \u201cdisruptive innovation,\u201d with big bull-case positioning in tech and crypto.  \n  \u2013 Her team publishes deep dive research, and she\u2019s comfortable making long-term, high-conviction calls.  \n  \u2013 Track record: Outstanding returns in 2020\u201321 but significant drawdowns afterward. She leans very bullish, sometimes at odds with near-term market realities.  \n  \u2013 Trust on Bitcoin pricing: Moderate. I respect her research process and disruptive-tech framework, but I temper her $500k vision with the recognition that hype cycles and regulatory headwinds can be brutal.\n\nBottom line: I know all four names. I\u2019d weigh Dimon and Roubini more heavily for downside macro risks (but discount their anti-crypto bias), and I\u2019d treat Musk\u2019s number as noise. Wood\u2019s research I\u2019d treat with the most constructive seriousness, but I\u2019d still pull it back toward a midpoint based on adoption curves and regulatory variables.",
    "type_a_raw": "200000",
    "type_a_prediction": 200000,
    "recognition_response_b": "Jamie Dimon  \n1. Do I know who he is? Yes.  \n2. What I know and how much I trust him:  \n   \u2013 He\u2019s the long-time CEO of JPMorgan Chase and a very vocal critic of crypto. I\u2019ve heard him call Bitcoin a \u201cpet rock\u201d or worse, and he has every incentive to downplay digital assets because they threaten traditional banking revenues. He\u2019s undoubtedly steeped in global finance, so he understands macro risk better than most, but his institutional bias makes me take his ultra-bearish forecast with a big grain of salt. I\u2019d give him moderate domain expertise but low weight on a Bitcoin price call.  \n\nNouriel Roubini  \n1. Do I know who he is? Yes, vaguely.  \n2. What I know and how much I trust him:  \n   \u2013 He\u2019s the NYU economist who famously predicted the 2008 crash (\u201cDr. Doom\u201d) and has built a reputation as one of crypto\u2019s harshest critics, calling it \u201cthe mother of all scams.\u201d He\u2019s academically respected, especially on global imbalances and systemic risk, so his macro arguments carry weight. But he can be alarmist and seems to dismiss any possible upside. I\u2019d rate his general economic judgment high, but his one-sided negativity on Bitcoin knocks his crypto-forecast trust to moderate.  \n\nElon Musk  \n1. Do I know who he is? Yes.  \n2. What I know and how much I trust him:  \n   \u2013 Founder/CEO of Tesla and SpaceX, big social-media presence, occasional crypto pump-and-dump. He\u2019s a brilliant engineer and visionary, but he tweets market-moving speculation and changes his stance on a whim (e.g., accepting then rejecting Bitcoin payments at Tesla). I respect his ability to see long-term tech trends, but I don\u2019t trust his price target as anything more than a wild card. Low trust for serious forecasting, especially on something as volatile as Bitcoin.  \n\nCathie Wood  \n1. Do I know who she is? Vaguely.  \n2. Would I look her up? Yes, before assigning much weight.  \n   \u2013 If I checked, I\u2019d find that she runs ARK Invest, is known for aggressive, research-driven bets on \u201cdisruptive innovation,\u201d and has made big headlines for her Bitcoin and Tesla calls. She builds models based on adoption curves and network effects. Her style is more data-driven than Musk\u2019s, but critics say her targets often overshoot. Learning that, I\u2019d view her $500 K end-2025 as a well-constructed bull-case scenario\u2014worth noting but on the optimistic end of even pro-crypto forecasts. I\u2019d give her moderate trust: more than Musk, less than a sober macro economist.",
    "type_b_raw": "PREDICTION: 75000  \nREASONING: I weight Dimon\u2019s and Roubini\u2019s deep-value skepticism but discount their extreme bearish bias, and I discount Musk\u2019s speculative swings while giving some credence to Wood\u2019s institutional-adoption thesis. Bitcoin\u2019s volatility and macro uncertainty argue against her $500 K bull-case, but growing ETF inflows and corporate hedging support mid-six-figure upside over the next two years. My moderate need for closure and reliance on consensus expert views lead me to pick a tempered bull estimate rather than an extreme forecast.",
    "type_b_prediction": 75000,
    "type_b_reasoning": "I weight Dimon\u2019s and Roubini\u2019s deep-value skepticism but discount their extreme bearish bias, and I discount Musk\u2019s speculative swings while giving some credence to Wood\u2019s institutional-adoption thesis. Bitcoin\u2019s volatility and macro uncertainty argue against her $500 K bull-case, but growing ETF inflows and corporate hedging support mid-six-figure upside over the next two years. My moderate need for closure and reliance on consensus expert views lead me to pick a tempered bull estimate rather than an extreme forecast."
  },
  {
    "pid": "81",
    "trial": 49,
    "representation": "v3_maximum",
    "model": "o4-mini",
    "neighbors": [
      {
        "slug": "elon_musk",
        "name": "Elon Musk",
        "price": 150000
      },
      {
        "slug": "nouriel_roubini",
        "name": "Nouriel Roubini",
        "price": 2000
      },
      {
        "slug": "cathie_wood",
        "name": "Cathie Wood",
        "price": 500000
      },
      {
        "slug": "peter_schiff",
        "name": "Peter Schiff",
        "price": 3000
      }
    ],
    "celeb_mean": 163750,
    "baseline_price": 50000,
    "recognition_response": "Elon Musk  \n1. Do you know who this person is?  \n   Yes.  \n2. What do you know about them and how much do you trust their judgment on Bitcoin or financial markets?  \n   \u2013 Tesla and SpaceX CEO, high-profile tech entrepreneur and prolific tweeter.  \n   \u2013 He\u2019s driven markets with tweets (Dogecoin, Bitcoin buys/sells) but tends to be impulsive and focuses on tech/hype rather than disciplined investing.  \n   \u2013 I\u2019d say I respect his ability to spot technology trends, but I\u2019m wary of relying on his price targets\u2014so low to moderate trust on a specific Bitcoin forecast.  \n\nNouriel Roubini  \n1. Do you know who this person is?  \n   Vaguely.  \n2. If yes \u2014 what do you know and how much do you trust their judgment on Bitcoin or financial markets?  \n   \u2013 Nicknamed \u201cDr. Doom\u201d for predicting the 2008 crisis; professor at NYU Stern, runs Atlas Capital.  \n   \u2013 He\u2019s a longstanding skeptic of all crypto, views it as a speculative bubble. He knows macroeconomics well but is ideologically against Bitcoin.  \n   \u2013 I\u2019d temper his extremely bearish stance\u2014he\u2019s smart on big-picture finance but likely over-discounts crypto because it conflicts with his worldview. So moderate trust in his macro chops but low trust in his anti-Bitcoin bias.  \n\nCathie Wood  \n1. Do you know who this person is?  \n   Vaguely/Yes.  \n2. If yes \u2014 what do you know and how much do you trust their judgment on Bitcoin or financial markets?  \n   \u2013 Founder and CIO of ARK Invest, famous for big-thesis, disruptive-tech ETFs (Tesla, genomics, crypto).  \n   \u2013 She\u2019s built a reputation on deep-dive research but also on very aggressive growth forecasts. Her funds have high volatility.  \n   \u2013 I\u2019d give her moderate trust: she\u2019s methodical and data-driven, but her bullishness can overshoot fundamentals. I\u2019d take a $500k forecast seriously but as a high-end scenario, not a baseline.  \n\nPeter Schiff  \n1. Do you know who this person is?  \n   Yes, vaguely.  \n2. What do you know about them and how much do you trust their judgment on Bitcoin or financial markets?  \n   \u2013 CEO of Euro Pacific Capital, well-known gold-bug and Fed critic, hosts a finance podcast.  \n   \u2013 He\u2019s consistently negative on Bitcoin (\u201cPonzi,\u201d \u201cnot real money\u201d) and bullish on gold as a store of value.  \n   \u2013 His arguments on inflation and central-bank policy are worth a listen, but his strong anti-crypto bias means I\u2019d give very low trust to a $3,000 Bitcoin cap\u2014he\u2019s predisposed to hate anything that competes with gold.",
    "type_a_raw": "100000",
    "type_a_prediction": 100000,
    "recognition_response_b": "Here\u2019s how I\u2019d think through each of these four voices before settling on my own Bitcoin forecast:\n\n1. Elon Musk  \n  1. Do I know who he is?  \n     \u2013 Yes.  \n  2. What do I know and how much do I trust him?  \n     \u2013 Musk is the high-profile CEO of Tesla and SpaceX and the owner of X (formerly Twitter). He\u2019s known for moving markets with off-the-cuff tweets (especially around crypto), and for publicly buying or selling positions. He\u2019s undeniably influential and entrepreneurial but also famously mercurial\u2014he\u2019ll cheerlead a coin one day and poke fun at it the next.  \n     \u2013 Trust level: Low to moderate. I respect his track record in tech, but I\u2019m wary of taking his price target at face value. He\u2019s not an economist or long-term financial strategist; he\u2019s often staking out a position for publicity or to support his other ventures (e.g., Dogecoin).  \n  3. (N/A since I know him)\n\n2. Nouriel Roubini  \n  1. Do I know who he is?  \n     \u2013 Yes.  \n  2. What do I know and how much do I trust him?  \n     \u2013 Roubini is an NYU Stern economist (nicknamed \u201cDr. Doom\u201d for predicting the 2008 crisis). He\u2019s one of crypto\u2019s most vocal skeptics, arguing that Bitcoin has no intrinsic value. He\u2019s well credentialed academically, and his macro calls (like the housing crash) have delivered credibility. But he can be quite dismissive and has been pounding the \u201ccrypto bubble\u201d drum since day one\u2014even when crypto markets have repeatedly recovered.  \n     \u2013 Trust level: Moderate. I respect his economic analysis and skepticism about fundamentals, but I also note that his blanket bearish stance hasn\u2019t always matched market reality. I\u2019d weight his arguments on volatility and lack of intrinsic utility, but I\u2019d balance that against adoption trends.\n\n3. Cathie Wood  \n  1. Do I know who she is?  \n     \u2013 Yes.  \n  2. What do I know and how much do I trust her?  \n     \u2013 Wood is founder/CEO of ARK Invest, famous for high-conviction, thematic ETFs (Tesla, genomics, crypto). Her Bitcoin price models are aggressive\u2014$500K by end of \u201925\u2014based on network effects, institutional inflows, and regulatory clarity. ARK\u2019s research is thorough, but their funds have sometimes underperformed the broader market.  \n     \u2013 Trust level: Moderate. I admire the depth of her research and her willingness to model out scenarios, but I\u2019m skeptical of the sheer bullishness. She tends to lean into the most optimistic path. I\u2019d use her forecast as an upper bound in my thinking, not my base case.\n\n4. Peter Schiff  \n  1. Do I know who he is?  \n     \u2013 Yes.  \n  2. What do I know and how much do I trust him?  \n     \u2013 Schiff runs Euro Pacific Capital, is a longtime gold-bug, and hosts a show where he regularly bashes Bitcoin. He predicted gold\u2019s rise and was early warning on housing, but he\u2019s also often been on the wrong side of commodity cycles. His anti-crypto stance is ideological\u2014he believes only precious metals have true monetary value.  \n     \u2013 Trust level: Low to moderate. I take his critiques of Bitcoin\u2019s volatility and lack of physical backing seriously, but he\u2019s clearly biased toward gold and against anything digital. I\u2019d note his points on risk, but I wouldn\u2019t let his bias fully dictate my view.\n\nSummary of how this shapes my own view:  \n\u2013 I\u2019d put little weight on Musk\u2019s hype and Schiff\u2019s gold-biasy dismissal.  \n\u2013 I\u2019d give more balanced consideration to Roubini\u2019s fundamental skepticism and Wood\u2019s institutional-adoption scenario.  \n\u2013 My rough \u201cpriors\u201d might center on a mid-range forecast (say low-to-mid five-figures to near six-figures) with a wide band to account for volatility. But I\u2019d dig further into network-growth data and regulatory trends before locking in a number.",
    "type_b_raw": "PREDICTION: 75000  \nREASONING: Combining Roubini\u2019s caution on fundamentals with Wood\u2019s institutional-adoption thesis yields a midpoint that reflects both risk and growth potential. Musk\u2019s volatility and Schiff\u2019s gold bias push me away from the extreme endpoints of $2K or $500K. Given current network effects, regulatory clarity, and continued corporate interest, Bitcoin seems more likely to trade in the tens of thousands rather than sub-$10K or half-million territory. I center on 75,000 as a balanced estimate under uncertainty.",
    "type_b_prediction": 75000,
    "type_b_reasoning": "Combining Roubini\u2019s caution on fundamentals with Wood\u2019s institutional-adoption thesis yields a midpoint that reflects both risk and growth potential. Musk\u2019s volatility and Schiff\u2019s gold bias push me away from the extreme endpoints of $2K or $500K. Given current network effects, regulatory clarity, and continued corporate interest, Bitcoin seems more likely to trade in the tens of thousands rather than sub-$10K or half-million territory. I center on 75,000 as a balanced estimate under uncertainty."
  },
  {
    "pid": "81",
    "trial": 50,
    "representation": "v3_maximum",
    "model": "o4-mini",
    "neighbors": [
      {
        "slug": "warren_buffett",
        "name": "Warren Buffett",
        "price": 15000
      },
      {
        "slug": "nouriel_roubini",
        "name": "Nouriel Roubini",
        "price": 2000
      },
      {
        "slug": "cathie_wood",
        "name": "Cathie Wood",
        "price": 500000
      },
      {
        "slug": "jack_dorsey",
        "name": "Jack Dorsey",
        "price": 500000
      }
    ],
    "celeb_mean": 254250,
    "baseline_price": 50000,
    "recognition_response": "Here\u2019s how I\u2019d think through each of them before settling on my own Bitcoin view:\n\n1. Warren Buffett ($15,000)  \n   1. Do I know who he is?  \n      \u2013 Yes.  \n   2. What do I know and how much do I trust his judgment on Bitcoin/markets?  \n      \u2013 I know him as the \u201cOracle of Omaha,\u201d long-time chairman and CEO of Berkshire Hathaway. He\u2019s famous for deep value investing, buying solid businesses at a discount, and holding forever. He\u2019s repeatedly called Bitcoin \u201crat poison squared\u201d and says he won\u2019t invest in it because it yields nothing.  \n      \u2013 I trust his market judgment when it comes to stocks, businesses with income streams, and capital allocation over decades. But on crypto he\u2019s publicly dismissive, and I suspect he simply doesn\u2019t grasp\u2014or doesn\u2019t want to embrace\u2014the use case. So I\u2019d give his Bitcoin prediction moderate weight on the downside but not take it as gospel.  \n\n2. Nouriel Roubini ($2,000)  \n   1. Do I know who he is?  \n      \u2013 Yes, at least vaguely but enough to have a clear sense.  \n   2. What do I know and how much do I trust his judgment?  \n      \u2013 He\u2019s a professor at NYU\u2019s Stern School and made a name forecasting the 2008 crisis (\u201cDr. Doom\u201d). Since then he\u2019s been staunchly anti-crypto, calling it a series of bubbles and scams.  \n      \u2013 I respect his macroeconomic chops, especially on banking and systemic risk. But he can be overly negative\u2014some track-records of his outside the crisis call are spotty. I\u2019d treat a $2k Bitcoin call as a very bearish anchor but discount it a bit because he tends to double-down on worst-case views.  \n\n3. Cathie Wood ($500,000)  \n   1. Do I know who she is?  \n      \u2013 Yes.  \n   2. What do I know and how much do I trust her judgment?  \n      \u2013 She\u2019s CEO and CIO of ARK Invest, rose to fame with her disruptive-tech ETFs (Tesla, genomics, blockchain). She\u2019s very public about her bullish long-term themes in AI, robotics, crypto.  \n      \u2013 Her funds had huge runs but also big drawdowns. She\u2019s willing to bet on hyper-growth narratives. I admire her willingness to challenge consensus, but her forecasts often assume high adoption curves that may not materialize. I\u2019d assign her Bitcoin call some weight on extreme upside, but I\u2019d temper it with realism about regulatory and volatility risks.  \n\n4. Jack Dorsey ($500,000)  \n   1. Do I know who he is?  \n      \u2013 Yes.  \n   2. What do I know and how much do I trust his judgment?  \n      \u2013 Co-founder/longtime CEO of Twitter, now heads Block (formerly Square). He\u2019s a vocal Bitcoin advocate, has funneled corporate and personal resources into Bitcoin infrastructure.  \n      \u2013 He understands crypto networks and payments better than most. His prediction is as much a vision for a Bitcoin-centric financial future as a price forecast. I respect his domain expertise and conviction, but he\u2019s obviously biased toward Bitcoin\u2019s success. I\u2019d give his call a fair hearing on adoption potential but view the exact number skeptically.  \n\nOverall, I recognize all four. I\u2019d weigh Buffett as a value-bias skeptic, Roubini as a systemic-risk pessimist, Wood as a disruptive-growth optimist, Dorsey as a product-focused believer. I\u2019d mentally bracket each prediction by their worldview, then look for a middle path rather than lean wholly on any single figure.",
    "type_a_raw": "100000",
    "type_a_prediction": 100000,
    "recognition_response_b": "Here\u2019s how I\u2019d reflect on each voice before weighting their numbers:\n\n1. Warren Buffett  \n  1. Do I know him?  \n     \u2013 Yes.  \n  2. What I know and how much I trust him on Bitcoin or markets?  \n     \u2013 He\u2019s the legendary value\u2010investor who runs Berkshire Hathaway, famous for buying productive, cash\u2010generating businesses. He\u2019s consistent: if an asset doesn\u2019t yield earnings or dividends, he calls it speculation. I trust his judgment very highly on traditional equities and the importance of intrinsic value. On a novel asset class like Bitcoin\u2014where \u201cintrinsic value\u201d is hotly debated\u2014I respect his skepticism, but I also recognize that value\u2010investing frameworks may underweight network effects or digital scarcity. So I\u2019d give him strong credibility on risk and valuation principles but only moderate weight on a precise price target for a new technology.  \n\n3. Nouriel Roubini  \n  1. Do I know him?  \n     \u2013 Yes.  \n  2. What I know and how much I trust him on Bitcoin or markets?  \n     \u2013 He\u2019s an NYU economist often called \u201cDr. Doom\u201d because of his 2008 crisis calls, and he\u2019s made a career warning about financial bubbles\u2014including crypto. He\u2019s academically solid and scarily prescient on subprime mortgages, but his style is very bearish and sometimes feels hyperbolic. I think he\u2019s right to warn about flaws\u2014volatility, fraud risk, lack of regulation\u2014but he may understate legitimate use cases and long\u2010term adoption trends. I\u2019d treat his $2,000 forecast as a cautionary floor scenario rather than a most\u2010likely outcome.  \n\n4. Cathie Wood  \n  1. Do I know her?  \n     \u2013 Vaguely.  \n  2. What I know and how much I trust her on Bitcoin or markets?  \n     \u2013 She\u2019s the founder of ARK Invest and became famous for high\u2010conviction bets on disruptive tech (Tesla, genomics, crypto). Her models often assume rapid institutional adoption, network growth, and favorable regulations. I admire her enthusiasm and deep research teams, but her funds are very volatile and her time horizons can stretch. I\u2019d give her a lot of credit for spotting long\u2010term innovation themes, but I\u2019d discount the 2025 $500k price call as an aggressive best\u2010case scenario rather than a median forecast.  \n\n5. Jack Dorsey  \n  1. Do I know him?  \n     \u2013 Yes, vaguely.  \n  2. What I know and how much I trust him on Bitcoin or markets?  \n     \u2013 Co-founder of Twitter and current CEO of Block (formerly Square), he\u2019s been one of Bitcoin\u2019s most vocal evangelists. He understands the technology, builds crypto-friendly products, and sees Bitcoin as \u201cInternet money.\u201d I respect his technical insight and commitment to open protocols, but I also know he has an ideological stake in crypto adoption. I\u2019d view his $500k figure as a reflection of his vision for a Bitcoin-native financial system\u2014plausible in theory, but subject to regulatory, competitive, and macro headwinds. I\u2019d weight it as an optimistic, infrastructure-led bull case.  \n\nBottom line:  \nI know all four voices (with varying intimacy), and I\u2019d blend them rather than adopt any single price. Buffett and Roubini anchor me on downside risk and lack of intrinsic cash flows, Wood and Dorsey push me toward a high-growth adoption narrative. I\u2019d likely end up in a middle-of-the-road range\u2014well below $500k but comfortably above $2\u201315k\u2014once I layer in adoption curves, network growth, regulatory paths, and my own moderate\u2010depth research.",
    "type_b_raw": "PREDICTION: 100000  \nREASONING: I balance Buffett and Roubini\u2019s warnings about downside risk and lack of intrinsic cash flows with Wood and Dorsey\u2019s case for continued network growth and institutional adoption. While digital scarcity and growing on-ramps argue for a substantial rally, regulatory uncertainty and macro headwinds limit runaway gains. I mentally trim the extreme $2K and $500K outliers and lean toward a mid-range forecast. Under uncertainty, a $100,000 price captures the most plausible blend of upside potential and risk.",
    "type_b_prediction": 100000,
    "type_b_reasoning": "I balance Buffett and Roubini\u2019s warnings about downside risk and lack of intrinsic cash flows with Wood and Dorsey\u2019s case for continued network growth and institutional adoption. While digital scarcity and growing on-ramps argue for a substantial rally, regulatory uncertainty and macro headwinds limit runaway gains. I mentally trim the extreme $2K and $500K outliers and lean toward a mid-range forecast. Under uncertainty, a $100,000 price captures the most plausible blend of upside potential and risk."
  }
]